postgresql_ldap_sync/__init__.py
postgresql_ldap_sync/clients/__init__.py
postgresql_ldap_sync/clients/ldap/__init__.py
postgresql_ldap_sync/clients/ldap/base.py
postgresql_ldap_sync/clients/ldap/dummy.py
postgresql_ldap_sync/clients/ldap/glauth.py
postgresql_ldap_sync/clients/psql/__init__.py
postgresql_ldap_sync/clients/psql/base.py
postgresql_ldap_sync/clients/psql/dummy.py
postgresql_ldap_sync/clients/psql/postgres.py
postgresql_ldap_sync/matcher.py
postgresql_ldap_sync/models/__init__.py
postgresql_ldap_sync/models/group_matches.py
postgresql_ldap_sync/models/group_members.py
postgresql_ldap_sync/models/user_matches.py
postgresql_ldap_sync/syncher.py
postgresql_ldap_sync-0.3.2.dist-info/LICENSE
postgresql_ldap_sync-0.3.2.dist-info/METADATA
postgresql_ldap_sync-0.3.2.dist-info/WHEEL
postgresql_ldap_sync-0.3.2.dist-info/RECORD
